ramsey/__init__.py
ramsey/data.py
ramsey/experimental.py
ramsey/family.py
ramsey/nn.py
ramsey/_src/__init__.py
ramsey/_src/conftest.py
ramsey/_src/family.py
ramsey/_src/data/__init__.py
ramsey/_src/data/data.py
ramsey/_src/data/dataset_m4.py
ramsey/_src/experimental/__init__.py
ramsey/_src/experimental/bayesian_neural_network/__init__.py
ramsey/_src/experimental/bayesian_neural_network/bayesian_linear.py
ramsey/_src/experimental/bayesian_neural_network/bayesian_neural_network.py
ramsey/_src/experimental/bayesian_neural_network/train_bnn.py
ramsey/_src/experimental/distributions/__init__.py
ramsey/_src/experimental/distributions/autoregressive.py
ramsey/_src/experimental/gaussian_process/__init__.py
ramsey/_src/experimental/gaussian_process/gaussian_process.py
ramsey/_src/experimental/gaussian_process/sparse_gaussian_process.py
ramsey/_src/experimental/gaussian_process/train_gaussian_process.py
ramsey/_src/experimental/gaussian_process/kernel/__init__.py
ramsey/_src/experimental/gaussian_process/kernel/base.py
ramsey/_src/experimental/gaussian_process/kernel/distance.py
ramsey/_src/experimental/gaussian_process/kernel/non_stationary.py
ramsey/_src/experimental/gaussian_process/kernel/stationary.py
ramsey/_src/experimental/timeseries/__init__.py
ramsey/_src/experimental/timeseries/recurrent_attentive_neural_process.py
ramsey/_src/neural_process/__init__.py
ramsey/_src/neural_process/attentive_neural_process.py
ramsey/_src/neural_process/doubly_attentive_neural_process.py
ramsey/_src/neural_process/neural_process.py
ramsey/_src/neural_process/neural_process_test.py
ramsey/_src/neural_process/train_neural_process.py
ramsey/_src/neural_process/train_neural_process_test.py
ramsey/_src/nn/MLP.py
ramsey/_src/nn/__init__.py
ramsey/_src/nn/attention/__init__.py
ramsey/_src/nn/attention/attention.py
ramsey/_src/nn/attention/dotproduct_attention.py
ramsey/_src/nn/attention/multihead_attention.py
ramsey-0.2.1.dist-info/LICENSE
ramsey-0.2.1.dist-info/METADATA
ramsey-0.2.1.dist-info/WHEEL
ramsey-0.2.1.dist-info/top_level.txt
ramsey-0.2.1.dist-info/RECORD
