Metadata-Version: 2.1
Name: ramsey
Version: 0.2.1
Summary: Probabilistic deep learning using JAX
Home-page: https://github.com/ramsey-devs/ramsey
Author: The Ramsey developers
License: Apache 2.0
Keywords: bayes,jax,probabilistic deep learning,probabilistic models,neural process
Classifier: Development Status :: 1 - Planning
Classifier: Intended Audience :: Science/Research
Classifier: License :: OSI Approved :: Apache Software License
Classifier: Programming Language :: Python :: 3
Classifier: Programming Language :: Python :: 3.9
Classifier: Programming Language :: Python :: 3.10
Classifier: Programming Language :: Python :: 3.11
Classifier: Programming Language :: Python :: 3.12
Requires-Python: >=3.9
License-File: LICENSE
Requires-Dist: chex
Requires-Dist: flax >=0.7.2
Requires-Dist: jax >=0.4.4
Requires-Dist: jaxlib >=0.4.4
Requires-Dist: numpyro
Requires-Dist: optax
Requires-Dist: pandas
Requires-Dist: rmsyutls
Requires-Dist: tqdm
Provides-Extra: dev
Requires-Dist: pre-commit ; extra == 'dev'
Requires-Dist: black ; extra == 'dev'
Requires-Dist: isort ; extra == 'dev'
Requires-Dist: pylint ; extra == 'dev'
Requires-Dist: tox ; extra == 'dev'
Requires-Dist: pytest ; extra == 'dev'
Provides-Extra: examples
Requires-Dist: matplotlib ; extra == 'examples'
